{
  "schema_version": 1,
  "owner": "admin05",
  "repository": {
    "id": 1265958639,
    "node_id": "R_kgDOS3T-7w",
    "name": "PlayMusic",
    "full_name": "admin05/PlayMusic",
    "html_url": "https://github.com/admin05/PlayMusic",
    "description": null,
    "homepage": null,
    "private": false,
    "visibility": "public",
    "archived": false,
    "disabled": false,
    "fork": false,
    "is_template": false,
    "default_branch": "main",
    "language": "JavaScript",
    "topics": [],
    "license": null,
    "created_at": "2026-06-11T08:02:42Z",
    "updated_at": "2026-06-11T08:34:50Z",
    "pushed_at": "2026-06-11T08:34:46Z",
    "size_kb": 14,
    "stars": 0,
    "forks": 0,
    "watchers": 0,
    "open_issues_and_pulls": 0,
    "has_issues": true,
    "has_projects": true,
    "has_wiki": false,
    "has_pages": false,
    "has_discussions": false
  },
  "collected_at": "2026-07-21T00:14:41Z",
  "metadata_history": [
    {
      "date": "2026-07-20",
      "stars": 0,
      "forks": 0,
      "watchers": 0,
      "open_issues_and_pulls": 0,
      "size_kb": 14
    },
    {
      "date": "2026-07-21",
      "stars": 0,
      "forks": 0,
      "watchers": 0,
      "open_issues_and_pulls": 0,
      "size_kb": 14
    }
  ],
  "languages": {
    "JavaScript": 9815
  },
  "community": {
    "health_percentage": 14,
    "description": null,
    "documentation": null,
    "files": {
      "code_of_conduct": null,
      "code_of_conduct_file": null,
      "contributing": null,
      "issue_template": null,
      "pull_request_template": null,
      "license": null,
      "readme": {
        "url": "https://api.github.com/repos/admin05/PlayMusic/contents/README.md",
        "html_url": "https://github.com/admin05/PlayMusic/blob/main/README.md"
      }
    },
    "updated_at": null
  },
  "counts": {
    "contributors": 1,
    "branches": 1,
    "tags": 0,
    "releases": 0,
    "open_pull_requests": 0
  },
  "participation": {
    "all": [
      0,
      0,
      0,
      0,
      0,
      0,
      0,
      0,
      0,
      0,
      0,
      0,
      0,
      0,
      0,
      0,
      0,
      0,
      0,
      0,
      0,
      0,
      0,
      0,
      0,
      0,
      0,
      0,
      0,
      0,
      0,
      0,
      0,
      0,
      0,
      0,
      0,
      0,
      0,
      0,
      0,
      0,
      0,
      0,
      0,
      0,
      4,
      0,
      0,
      0,
      0,
      0
    ],
    "owner": [
      0,
      0,
      0,
      0,
      0,
      0,
      0,
      0,
      0,
      0,
      0,
      0,
      0,
      0,
      0,
      0,
      0,
      0,
      0,
      0,
      0,
      0,
      0,
      0,
      0,
      0,
      0,
      0,
      0,
      0,
      0,
      0,
      0,
      0,
      0,
      0,
      0,
      0,
      0,
      0,
      0,
      0,
      0,
      0,
      0,
      0,
      0,
      0,
      0,
      0,
      0,
      0
    ]
  },
  "traffic": {
    "views": [
      {
        "timestamp": "2026-07-05T00:00:00Z",
        "count": 0,
        "uniques": 0
      },
      {
        "timestamp": "2026-07-06T00:00:00Z",
        "count": 0,
        "uniques": 0
      },
      {
        "timestamp": "2026-07-07T00:00:00Z",
        "count": 0,
        "uniques": 0
      },
      {
        "timestamp": "2026-07-08T00:00:00Z",
        "count": 0,
        "uniques": 0
      },
      {
        "timestamp": "2026-07-09T00:00:00Z",
        "count": 0,
        "uniques": 0
      },
      {
        "timestamp": "2026-07-10T00:00:00Z",
        "count": 0,
        "uniques": 0
      },
      {
        "timestamp": "2026-07-11T00:00:00Z",
        "count": 0,
        "uniques": 0
      },
      {
        "timestamp": "2026-07-12T00:00:00Z",
        "count": 0,
        "uniques": 0
      },
      {
        "timestamp": "2026-07-13T00:00:00Z",
        "count": 0,
        "uniques": 0
      },
      {
        "timestamp": "2026-07-14T00:00:00Z",
        "count": 0,
        "uniques": 0
      },
      {
        "timestamp": "2026-07-15T00:00:00Z",
        "count": 0,
        "uniques": 0
      },
      {
        "timestamp": "2026-07-16T00:00:00Z",
        "count": 0,
        "uniques": 0
      },
      {
        "timestamp": "2026-07-17T00:00:00Z",
        "count": 0,
        "uniques": 0
      },
      {
        "timestamp": "2026-07-18T00:00:00Z",
        "count": 0,
        "uniques": 0
      },
      {
        "timestamp": "2026-07-19T00:00:00Z",
        "count": 0,
        "uniques": 0
      }
    ],
    "clones": [
      {
        "timestamp": "2026-07-05T00:00:00Z",
        "count": 0,
        "uniques": 0
      },
      {
        "timestamp": "2026-07-06T00:00:00Z",
        "count": 0,
        "uniques": 0
      },
      {
        "timestamp": "2026-07-07T00:00:00Z",
        "count": 0,
        "uniques": 0
      },
      {
        "timestamp": "2026-07-08T00:00:00Z",
        "count": 1,
        "uniques": 1
      },
      {
        "timestamp": "2026-07-09T00:00:00Z",
        "count": 0,
        "uniques": 0
      },
      {
        "timestamp": "2026-07-10T00:00:00Z",
        "count": 0,
        "uniques": 0
      },
      {
        "timestamp": "2026-07-11T00:00:00Z",
        "count": 0,
        "uniques": 0
      },
      {
        "timestamp": "2026-07-12T00:00:00Z",
        "count": 1,
        "uniques": 1
      },
      {
        "timestamp": "2026-07-13T00:00:00Z",
        "count": 1,
        "uniques": 1
      },
      {
        "timestamp": "2026-07-14T00:00:00Z",
        "count": 0,
        "uniques": 0
      },
      {
        "timestamp": "2026-07-15T00:00:00Z",
        "count": 0,
        "uniques": 0
      },
      {
        "timestamp": "2026-07-16T00:00:00Z",
        "count": 0,
        "uniques": 0
      },
      {
        "timestamp": "2026-07-17T00:00:00Z",
        "count": 0,
        "uniques": 0
      },
      {
        "timestamp": "2026-07-18T00:00:00Z",
        "count": 0,
        "uniques": 0
      },
      {
        "timestamp": "2026-07-19T00:00:00Z",
        "count": 0,
        "uniques": 0
      }
    ],
    "popular_paths": [
      {
        "date": "2026-07-20",
        "captured_at": "2026-07-20T03:57:47Z",
        "items": []
      },
      {
        "date": "2026-07-21",
        "captured_at": "2026-07-21T00:14:41Z",
        "items": []
      }
    ],
    "popular_referrers": [
      {
        "date": "2026-07-20",
        "captured_at": "2026-07-20T03:57:47Z",
        "items": []
      },
      {
        "date": "2026-07-21",
        "captured_at": "2026-07-21T00:14:41Z",
        "items": []
      }
    ]
  },
  "collection_errors": []
}
